{"stem":"1917","instances":[{"docId":"D041538","docUri":"D041538.html","score":2,"contexts":[{"form":"1917","weight":"2","pos":4,"context":"Tagebuch von Arthur Schnitzler, 22. 2. <mark>1917<\/mark>","fid":"page"}]},{"docId":"D041542","docUri":"D041542.html","score":2,"contexts":[{"form":"1917","weight":"2","pos":4,"context":"Tagebuch von Arthur Schnitzler, 26. 5. <mark>1917<\/mark>","fid":"page"}]},{"docId":"D041299","docUri":"D041299.html","score":2,"contexts":[{"form":"1917","weight":"2","pos":4,"context":"Tagebuch von Arthur Schnitzler, 27. 1. <mark>1917<\/mark>","fid":"page"}]},{"docId":"D041540","docUri":"D041540.html","score":2,"contexts":[{"form":"1917","weight":"2","pos":4,"context":"Tagebuch von Arthur Schnitzler, 18. 3. <mark>1917<\/mark>","fid":"page"}]},{"docId":"D041541","docUri":"D041541.html","score":2,"contexts":[{"form":"1917","weight":"2","pos":4,"context":"Tagebuch von Arthur Schnitzler, 19. 5. <mark>1917<\/mark>","fid":"page"}]},{"docId":"D041539","docUri":"D041539.html","score":2,"contexts":[{"form":"1917","weight":"2","pos":4,"context":"Tagebuch von Arthur Schnitzler, 13. 3. <mark>1917<\/mark>","fid":"page"}]},{"docId":"D041481","docUri":"D041481.html","score":2,"contexts":[{"form":"1917","weight":"2","pos":6,"context":"...Bahr: [Reiseplanung für Wienaufenthalt], [Februar <mark>1917<\/mark>]","fid":"page"}]}]}