{"stem":"abfällig","instances":[{"docId":"D041120","docUri":"D041120.html","score":1,"contexts":[{"form":"abfällige","weight":"1","pos":47,"context":"..., »die nie Zeitung liest« wüthend über eine <mark>abfällige<\/mark> Kritik im »Weltblatt« – und als ich...","fid":"p__9"}]},{"docId":"T030081","docUri":"T030081.html","score":1,"contexts":[{"form":"abfällig","weight":"1","pos":500,"context":"...Burckhard, wir plaudern, er äussert sich ziemlich <mark>abfällig<\/mark> über das Radfahren.","fid":"p__30"}]}]}