{"stem":"aufdrängen","instances":[{"docId":"L041381","docUri":"L041381.html","score":1,"contexts":[{"form":"aufdrängen","weight":"1","pos":40,"context":"...empfinde gleich wieder, jetzt wo die alten Verhältnisse sich <mark>aufdrängen<\/mark>, das vielfach unzulängliche, unter dem man zu...","fid":"p__14"}]},{"docId":"D041506","docUri":"D041506.html","score":1,"contexts":[{"form":"aufdrängen","weight":"1","pos":54,"context":"...einzureden (die ihr natürlich alle, zuerst Bruno Walter, <mark>aufdrängen<\/mark> wollen, jeder möchte der »Nachfolger« sein) u....","fid":"p__13"}]}]}