{"stem":"aufzuzeichnen","instances":[{"docId":"T030057","docUri":"T030057.html","score":1,"contexts":[{"form":"aufzuzeichnen","weight":"1","pos":186,"context":"..., wäre es dir der Mühe wert gewesen, es <mark>aufzuzeichnen<\/mark> oder gar in die Zeitung zu setzen?","fid":"p__15"}]},{"docId":"D041495","docUri":"D041495.html","score":1,"contexts":[{"form":"aufzuzeichnen","weight":"1","pos":136,"context":"...ein Koloisches Quadratlpapier gekauft, um das Ganze <mark>aufzuzeichnen<\/mark>, wobei ich mir nur immer wünschte, Du...","fid":"p__23"}]}]}