{"stem":"balser","instances":[{"docId":"L041461","docUri":"L041461.html","score":1,"contexts":[{"form":"Balser","weight":"1","pos":109,"context":"Im Burgtheater spielt nächstens <mark>Balser<\/mark> den Puppenspieler, – gemildert durch den Faun von...","fid":"p__14"}]},{"docId":"D041536","docUri":"D041536.html","score":1,"contexts":[{"form":"Balser","weight":"1","pos":10,"context":"...»General Pr.« Puppenspieler; recht sehr wirkend.– <mark>Balser<\/mark> wäre mein Schauspieler;– nur – sagt ich zu...","fid":"p__19"}]}]}