{"stem":"beneiden","instances":[{"docId":"L041480","docUri":"L041480.html","score":1,"contexts":[{"form":"beneiden","weight":"1","pos":31,"context":"...sein. Im übrigen liegt mancher Anlaß vor, mich zu <mark>beneiden<\/mark>; – wenigstens für die abgelaufenen vier Wochen;...","fid":"p__16"}]},{"docId":"L041697","docUri":"L041697.html","score":1,"contexts":[{"form":"Beneiden","weight":"1","pos":24,"context":"      Fritz Schlesinger G Franckenste in <mark>Beneiden<\/mark> Sie uns ein bisserl, ja? Gerty HerzGruss ArthSchnitzler...","fid":"div__28"}]}]}