{"stem":"benützen","instances":[{"docId":"D041258","docUri":"D041258.html","score":1,"contexts":[{"form":"benützen","weight":"1","pos":29,"context":"...die Sache auf und gestatte ihm den Brief zu <mark>benützen<\/mark>.– Es thut mir nun leid, mit den...","fid":"p__4"}]},{"docId":"L041509","docUri":"L041509.html","score":1,"contexts":[{"form":"benützen","weight":"1","pos":70,"context":"...Lido, und für Venedig – und für uns <mark>benützen<\/mark>? Paula und ich wären sehr froh. Wir...","fid":"p__11"}]},{"docId":"D041368","docUri":"D041368.html","score":1,"contexts":[{"form":"benützen","weight":"1","pos":79,"context":"...Fremdenblatt; nun scheints will man das zu Gagendruck <mark>benützen<\/mark>. Aus Konstantinopel. Mißhelligkeiten zwischen Deutschen und Bulgaren...","fid":"p__9"}]},{"docId":"L041262","docUri":"L041262.html","score":1,"contexts":[{"form":"benützen","weight":"1","pos":45,"context":"...am End erst seine Köchin anflehen muß, sie zu <mark>benützen<\/mark>. ","fid":"p__8"}]},{"docId":"L041492","docUri":"L041492.html","score":1,"contexts":[{"form":"benützen","weight":"1","pos":18,"context":"...zu installieren und gedenke hauptsächlich die Zeit dazu zu <mark>benützen<\/mark> um mit Ihnen wieder einmal Pläne für die nächste...","fid":"p__4"}]}]}