{"stem":"buz","instances":[{"docId":"D041590","docUri":"D041590.html","score":1,"contexts":[{"form":"Buz","weight":"1","pos":9,"context":"...– Mit Olga Schnitzler über Mönchsberg. – Anna <mark>Buz<\/mark> nach Augsburg. – An Anna.  Journaltgb ....","fid":"p__10"}]},{"docId":"D041584","docUri":"D041584.html","score":1,"contexts":[{"form":"Buz","weight":"1","pos":38,"context":"..., dessen Herrin einst Lola Montez war. – Der <mark>Buz<\/mark> geht es besser, doch sie muß noch fest eingewickelt...","fid":"p__10"}]},{"docId":"T030075","docUri":"T030075.html","score":1,"contexts":[{"form":"Buz","weight":"1","pos":93,"context":" Anna <mark>Buz<\/mark> ","fid":"p__231"}]}]}