{"stem":"bänden","instances":[{"docId":"L041399","docUri":"L041399.html","score":1,"contexts":[{"form":"Bänden","weight":"1","pos":101,"context":"...ich nicht recht, wie man in drei bis vier <mark>Bänden<\/mark> eine Zusammenfassung meiner Arbeiten versuchen könnte, ohne ein recht...","fid":"p__19"}]},{"docId":"L041346","docUri":"L041346.html","score":1,"contexts":[{"form":"Bänden","weight":"1","pos":297,"context":"...halten: »Ausgewähltes Theater«, in wie viel <mark>Bänden<\/mark>?, oder Auswahl der Romane, beziehungsweise was mir...","fid":"p__15"}]},{"docId":"L041564","docUri":"L041564.html","score":1,"contexts":[{"form":"Bänden","weight":"1","pos":52,"context":"...in diese Ausgabe aufzunehmen sind. Eine Auswahl in 3–4 <mark>Bänden<\/mark> zu einem billigen Preis (höchstens 12–15 Mark für...","fid":"p__5"}]},{"docId":"L041192","docUri":"L041192.html","score":1,"contexts":[{"form":"Bänden","weight":"1","pos":40,"context":"...concentrieren, daneben aber die Redaction von 3 schwierigen <mark>Bänden<\/mark> der Goethe-Ausgabe besorgen. Ich habe jetzt...","fid":"p__18"}]}]}