{"stem":"chiavacci","instances":[{"docId":"D041403","docUri":"D041403.html","score":2,"contexts":[{"form":"Chiavacci","weight":"1","pos":17,"context":" <mark>Chiavacci<\/mark> ","fid":"p__9"},{"form":"Chiavacci","weight":"1","pos":60,"context":" <mark>Chiavacci<\/mark> hat abgesagt ","fid":"p__154"}]},{"docId":"L041207","docUri":"L041207.html","score":1,"contexts":[{"form":"Chiavacci","weight":"1","pos":63,"context":" Vincenz <mark>Chiavacci<\/mark> ","fid":"p__177"}]},{"docId":"L041250","docUri":"L041250.html","score":1,"contexts":[{"form":"Chiavacci","weight":"1","pos":13,"context":"...Wisch hat Burckhard bekommen, voriges Jahr Karlweis und <mark>Chiavacci<\/mark>, und mit derselben Wirkung: einer Anfrage bei...","fid":"p__7"}]},{"docId":"D041168","docUri":"D041168.html","score":1,"contexts":[{"form":"Chiavacci","weight":"1","pos":10,"context":"...spazieren.– Bei Karlweis. Bahr, Burckhard, <mark>Chiavacci<\/mark>, Schwarzkopf, Bauer.","fid":"p__9"}]},{"docId":"D041404","docUri":"D041404.html","score":1,"contexts":[{"form":"Chiavacci","weight":"1","pos":13,"context":" x Karlweis , x Bucovics, x <mark>Chiavacci<\/mark>, x Gettke, Kutschera, x Berger ,...","fid":"p__39"}]},{"docId":"D041349","docUri":"D041349.html","score":1,"contexts":[{"form":"Chiavacci","weight":"1","pos":99,"context":"...Schönherr,– (Steuersachen) seine Frau (frühere <mark>Chiavacci<\/mark>) – über »Es«, u. s. w. Lili tanzte...","fid":"p__21"}]},{"docId":"D041146","docUri":"D041146.html","score":1,"contexts":[{"form":"Chiavacci","weight":"1","pos":32,"context":"...Kfh. Bahr über Andrian gesprochen.– Mit Frau <mark>Chiavacci<\/mark> und Engel im Kfh. Poker, verloren....","fid":"p__12"}]},{"docId":"D041069","docUri":"D041069.html","score":1,"contexts":[{"form":"Chiavacci","weight":"1","pos":13,"context":"...(nach flüchtiger Begegnung mit Bahr) J. Bauer und <mark>Chiavacci<\/mark>, die in einem Rondeau sich eben gegenüber liegen...","fid":"p__8"}]},{"docId":"L041217","docUri":"L041217.html","score":1,"contexts":[{"form":"Chiavacci","weight":"1","pos":24,"context":"...Speidel, Julius Bauer, Groß, Karlweis, <mark>Chiavacci<\/mark>, Ebermann, einige Maler, Bukovics, Gettke...","fid":"p__15"}]},{"docId":"T030078","docUri":"T030078.html","score":1,"contexts":[{"form":"Chiavacci","weight":"1","pos":35,"context":" <mark>Chiavacci<\/mark> : Die Spießer. Wirtshausleben.","fid":"p__9"}]},{"docId":"D041410","docUri":"D041410.html","score":1,"contexts":[{"form":"Chiavacci","weight":"1","pos":33,"context":"...Victor Adler  – Richard Specht – Dr  Holländer  –  <mark>Chiavacci<\/mark>  ","fid":"p__46"}]}]}