{"stem":"durchlaufen","instances":[{"docId":"T030004","docUri":"T030004.html","score":2,"contexts":[{"form":"durchlaufen","weight":"1","pos":642,"context":"...– und der Stoff hatte verschiedene Wandlungen und Fassungen <mark>durchlaufen<\/mark>; begonnen im Spätherbst 1893, langsam reifend,...","fid":"p__21"},{"form":"durchlaufen","weight":"1","pos":3393,"context":"...nach dem du angetreten « – Wieviele Phasen er <mark>durchlaufen<\/mark> haben mag, er ist geworden, was er von Anbeginn...","fid":"p__121"}]}]}