{"stem":"eil","instances":[{"docId":"L041560","docUri":"L041560.html","score":1,"contexts":[{"form":"Eile","weight":"1","pos":66,"context":"...mußte, durch die Gernot ersetzt wurde, in aller <mark>Eile<\/mark>; ich werde wohl den 2. Weihnachtsfeiertag, den...","fid":"p__14"}]},{"docId":"D041266","docUri":"D041266.html","score":1,"contexts":[{"form":"Eile","weight":"1","pos":37,"context":"...Er ging; ich wollte anfangs was unternehmen – aber <mark>Eile<\/mark> und Leichtfertigkeit hielten mich ab.–","fid":"p__17"}]},{"docId":"L041305","docUri":"L041305.html","score":1,"contexts":[{"form":"Eile","weight":"1","pos":30,"context":"...18 12. 2. 07 Lieber Artur!  In größter <mark>Eile<\/mark> mir vielen Grüßen an Deine Frau herzlichst Hermann ","fid":"div__20"}]},{"docId":"L041265","docUri":"L041265.html","score":1,"contexts":[{"form":"Eile","weight":"1","pos":34,"context":"...auf den 12. Dezember angesetzt. Warum plötzlich diese <mark>Eile<\/mark>, weiß ich nicht. Er kommt Montag im Imperial...","fid":"p__9"}]},{"docId":"L041665","docUri":"L041665.html","score":1,"contexts":[{"form":"Eile","weight":"1","pos":171,"context":".... 19. Nach Tisch.     Leb wol, in <mark>Eile<\/mark> alles Liebe, küss die Kinder tausendmal!  ","fid":"div__58"}]},{"docId":"L041635","docUri":"L041635.html","score":1,"contexts":[{"form":"Eile","weight":"1","pos":124,"context":" 24. 8. 04 Lieber Freund!           In <mark>Eile<\/mark> Ihr B. ","fid":"div__47"}]},{"docId":"L041206","docUri":"L041206.html","score":1,"contexts":[{"form":"Eile","weight":"1","pos":8,"context":"In aller <mark>Eile<\/mark>, mitten zwischen Correcturen und Schreibereien, möchte ich...","fid":"p__5"}]},{"docId":"L041208","docUri":"L041208.html","score":1,"contexts":[{"form":"Eile","weight":"1","pos":37,"context":" 22. März Lieber Arthur!  Herzlichst in großer <mark>Eile<\/mark> Dein Hermann ","fid":"div__25"}]},{"docId":"L041247","docUri":"L041247.html","score":1,"contexts":[{"form":"Eile","weight":"1","pos":41,"context":" 1. 4. Lieber Arthur!  Herzlichst in <mark>Eile<\/mark> Dein alter Hermann ","fid":"div__13"}]},{"docId":"D041327","docUri":"D041327.html","score":1,"contexts":[{"form":"Eile","weight":"1","pos":40,"context":"...fern Landungsbrücke, Gewühl verkleinert;– ich mahne zur <mark>Eile<\/mark>, ich sei bekannt, O. meint, hier nicht,...","fid":"p__38"}]},{"docId":"L041485","docUri":"L041485.html","score":1,"contexts":[{"form":"Eile","weight":"1","pos":23,"context":"...muß ich, da der Saal schon gemietet ist, in <mark>Eile<\/mark> ein anderes Programm machen und denke unter anderem auch...","fid":"p__12"}]}]}