{"stem":"entlang","instances":[{"docId":"L041671","docUri":"L041671.html","score":1,"contexts":[{"form":"entlang","weight":"1","pos":29,"context":"...Bahr,– gegen Maria-Plain an der Salzach <mark>entlang<\/mark>, unter einem herrlich farbenglühenden Himmel,– ich hab...","fid":"p__13"}]},{"docId":"D041327","docUri":"D041327.html","score":1,"contexts":[{"form":"entlang","weight":"1","pos":30,"context":"...auf der Spur;– wir laufen nun ein Ufer <mark>entlang<\/mark>, fremdartig, an einem Riesensee – gablig getheilt...","fid":"p__38"}]},{"docId":"D041141","docUri":"D041141.html","score":1,"contexts":[{"form":"entlang","weight":"1","pos":9,"context":".... Vorm. mit Mz. Rh. spazieren, Wien <mark>entlang<\/mark>; wie einst mit Mz.– Ich will nicht...","fid":"p__6"}]}]}