{"stem":"er","instances":[{"docId":"T030030","docUri":"T030030.html","score":1,"contexts":[{"form":"ers","weight":"1","pos":32,"context":"...in Brünn. Und die Beredsamkeit eines jungen Brünn<mark>ers<\/mark> hatte wirklich einen bisher unbescholtenen Buchdrucker so betörend verwirrt...","fid":"p__87"}]},{"docId":"T030004","docUri":"T030004.html","score":1,"contexts":[{"form":"er’s","weight":"1","pos":722,"context":"...zurückkommen werden«, entgegnet ihm Loris, »denn jetzt ist <mark>er’s<\/mark>.« ","fid":"p__23"}]},{"docId":"L041481","docUri":"L041481.html","score":1,"contexts":[{"form":"ers","weight":"1","pos":38,"context":"...Das schenken Dir Freunde Deiner Kunst, da nimmt <mark>ers<\/mark> gern. Er quittiert mir die Summen natürlich, denn es...","fid":"p__5"}]},{"docId":"D041295","docUri":"D041295.html","score":1,"contexts":[{"form":"ers","weight":"1","pos":20,"context":"...als ich die Erlaubnis verweigerte; angeblich besonders weil <mark>ers<\/mark> der Rossi versprochen.–","fid":"p__5"}]},{"docId":"L041457","docUri":"L041457.html","score":1,"contexts":[{"form":"er’s","weight":"1","pos":213,"context":"...und wahrscheinlich doch kein so merkwürdiges Individuum, als <mark>er’s<\/mark> nun durch das ist, was wir vielleicht fälschlich als...","fid":"p__13"}]},{"docId":"L041571","docUri":"L041571.html","score":1,"contexts":[{"form":"ers","weight":"1","pos":159,"context":"...nicht durch Deutschland kutschiert, in Venedig lebenden Prag<mark>ers<\/mark>, und vorige Woche Hofmannsthals, der eine jener...","fid":"p__24"}]},{"docId":"D041161","docUri":"D041161.html","score":1,"contexts":[{"form":"er’s","weight":"1","pos":80,"context":"...von der Sie schon zurückkommen werden – nun ist <mark>er’s<\/mark>.–","fid":"p__10"}]},{"docId":"L041460","docUri":"L041460.html","score":1,"contexts":[{"form":"ers","weight":"1","pos":50,"context":"...) meine Meinung über seine Komödie sagte. Nun hat <mark>ers<\/mark> erreicht, mit 62, – dass er aufgeführt wurde...","fid":"p__23"}]}]}