{"stem":"ersten","instances":[{"docId":"L041461","docUri":"L041461.html","score":1,"contexts":[{"form":"Erstens","weight":"1","pos":82,"context":"Meine Berliner Angelegenheiten ruhn. <mark>Erstens<\/mark> hat Lyonel für den »Weg« noch nichts...","fid":"p__11"}]},{"docId":"L041682","docUri":"L041682.html","score":1,"contexts":[{"form":"erstens","weight":"1","pos":34,"context":"...im Märchen spielen geht nicht – ich kann mich <mark>erstens<\/mark> nicht auf so lange Zeit – mindestens 8 Tage...","fid":"p__17"}]},{"docId":"L041562","docUri":"L041562.html","score":1,"contexts":[{"form":"erstens","weight":"1","pos":176,"context":"...mir vorschlagen: ich kann aber nicht nachschlagen, <mark>erstens<\/mark> weil ich kein Lexikon habe (und das ist mein...","fid":"p__46"}]},{"docId":"D041466","docUri":"D041466.html","score":1,"contexts":[{"form":"erstens","weight":"1","pos":339,"context":".... Er entschliesst sich, den jungen Grafen aufzusuchen, <mark>erstens<\/mark> um ihm sehr wehe zu tun (»das Bürscherl soll...","fid":"p__21"}]},{"docId":"T030026","docUri":"T030026.html","score":1,"contexts":[{"form":"Erstens","weight":"1","pos":292,"context":"...noch etwas kann ich an Schnitzler nicht verstehen. <mark>Erstens<\/mark> teilt er den Irrtum der Juden in Oesterreich,...","fid":"p__21"}]},{"docId":"L041210","docUri":"L041210.html","score":1,"contexts":[{"form":"Erstens","weight":"1","pos":16,"context":"...gut, wenn Sie sofort mit dem Drucke beginnen würden. <mark>Erstens<\/mark> weil ich jetzt mehr Muße habe, sorgfältig zu korrigieren...","fid":"p__7"}]},{"docId":"T030041","docUri":"T030041.html","score":1,"contexts":[{"form":"Erstens","weight":"1","pos":539,"context":"...Nur das ist ja logisch. – Zeuge: <mark>Erstens<\/mark> hätte ich Herrn Kraus überhaupt nicht berichtigt, und...","fid":"p__50"}]},{"docId":"L041209","docUri":"L041209.html","score":1,"contexts":[{"form":"erstens","weight":"1","pos":15,"context":"..., ob er mit uns lesen will? Ich habe <mark>erstens<\/mark> heute bis tief in die Nacht keine freie Minute...","fid":"p__6"}]},{"docId":"L041641","docUri":"L041641.html","score":1,"contexts":[{"form":"erstens","weight":"1","pos":68,"context":"...der Meister Erfolg (auch bei Berger ) enthebt Sie <mark>erstens<\/mark> solcher gewiss auf lange, und ich werde schon nichts...","fid":"p__42"}]},{"docId":"L041668","docUri":"L041668.html","score":1,"contexts":[{"form":"erstens","weight":"1","pos":304,"context":"...Übersetzung von Heinrich Mann, gelesen, und bin <mark>erstens<\/mark> sehr enttäuscht von der Übersetzung, die stellenweise in...","fid":"p__35"}]},{"docId":"D041458","docUri":"D041458.html","score":1,"contexts":[{"form":"erstens","weight":"1","pos":30,"context":"...vierzig Jahren« zu schreiben, um daran darzustellen, <mark>erstens<\/mark> jene merkwürdige dunkle fast komische Angst des vierzigsten Geburtstages...","fid":"p__6"}]},{"docId":"L041389","docUri":"L041389.html","score":1,"contexts":[{"form":"erstens","weight":"1","pos":13,"context":"...in Ohnmacht, da ich Ihnen umgehend antworte – <mark>erstens<\/mark> wollte ich dankend Brief und Einlagen bestätigen – drittens...","fid":"p__7"}]}]}