{"stem":"gemalt","instances":[{"docId":"T030004","docUri":"T030004.html","score":2,"contexts":[{"form":"gemalt","weight":"1","pos":298,"context":"...das ist das Bedeutendste, was seit zehn Jahren <mark>gemalt<\/mark> worden ist.«","fid":"p__17"},{"form":"gemalt","weight":"1","pos":1647,"context":"...Öffentlichkeit von der Wiener Universität, für die sie <mark>gemalt<\/mark> waren, zurückgewiesen wurden.","fid":"p__58"}]},{"docId":"D041459","docUri":"D041459.html","score":1,"contexts":[{"form":"gemalt","weight":"1","pos":103,"context":"...Aristokratinnen von einer Malerin, die einen montenegrinischen Mörder <mark>gemalt<\/mark>. Er habe sich »so gut benommen und beim...","fid":"p__14"}]},{"docId":"L041071","docUri":"L041071.html","score":1,"contexts":[{"form":"gemalt","weight":"1","pos":122,"context":"...ins Foyer hängen könnte, das Julian vor 25 Jahren <mark>gemalt<\/mark> und das ihn berühmt gemacht hat! Übrigens – vielleicht...","fid":"p__37"}]},{"docId":"D041078","docUri":"D041078.html","score":1,"contexts":[{"form":"gemalt","weight":"1","pos":9,"context":"...von Frl. Loewenstamm abgeholt. (Sie wird dort <mark>gemalt<\/mark>.)","fid":"p__4"}]},{"docId":"L041662","docUri":"L041662.html","score":1,"contexts":[{"form":"gemalt","weight":"1","pos":221,"context":"...bis 6 mit einer Verve und in einem Tempo <mark>gemalt<\/mark> hat,– na, ich sage nichts weiter, als bis das...","fid":"p__67"}]},{"docId":"L041238","docUri":"L041238.html","score":1,"contexts":[{"form":"gemalt","weight":"1","pos":89,"context":"...Philipps gehören und die ich mir großartig von Velasquez <mark>gemalt<\/mark> denken könnte.","fid":"p__23"}]}]}