{"stem":"grauen","instances":[{"docId":"T030012","docUri":"T030012.html","score":2,"contexts":[{"form":"Grauen","weight":"1","pos":676,"context":"...war doch nur ein Traum! Er aber, von <mark>Grauen<\/mark> und Ekel tief erfaßt, ruft aus:","fid":"p__8"},{"form":"Grauen","weight":"1","pos":1064,"context":"...dem Traurigen bis zum Tragischen, mit seinem tiefen <mark>Grauen<\/mark> vor dem Unbegreiflichen, das uns rings umgibt,...","fid":"p__26"}]},{"docId":"T030020","docUri":"T030020.html","score":2,"contexts":[{"form":"Grauen","weight":"1","pos":247,"context":"...gerade sehr vortreffliche Menschen solchen Dingen gegenüber eine Art <mark>Grauen<\/mark> empfinden mögen. Hausdorfer nickt: »Grauen – ja....","fid":"p__15"},{"form":"Grauen","weight":"1","pos":251,"context":"...eine Art Grauen empfinden mögen. Hausdorfer nickt: »<mark>Grauen<\/mark> – ja. Das wird schon das rechte Wort sein.«...","fid":"p__15"}]},{"docId":"D041466","docUri":"D041466.html","score":1,"contexts":[{"form":"Grauen","weight":"1","pos":358,"context":"...Anspielungen merkt, aber nicht versteht, ein geheimes <mark>Grauen<\/mark> vor einem solchen Menschen, wie er aus diesem Briefe...","fid":"p__21"}]},{"docId":"L041648","docUri":"L041648.html","score":1,"contexts":[{"form":"Grauen","weight":"1","pos":84,"context":"...der aus den russischen Kämpfen zurückkehrt meldet es mit <mark>Grauen<\/mark>. Sie wissen vielleicht von mir, lieber verehrter Hermann...","fid":"p__37"}]},{"docId":"L041356","docUri":"L041356.html","score":1,"contexts":[{"form":"grauen","weight":"1","pos":20,"context":"...in den weiten Park mit Schnee und auf die <mark>grauen<\/mark> Statue schaue, ist herrlich. Und ich denke...","fid":"p__6"}]},{"docId":"T030007","docUri":"T030007.html","score":1,"contexts":[{"form":"grauen","weight":"1","pos":65,"context":"...die – Und während ich mit rotgeweintem Aug’ Der <mark>grauen<\/mark> Dämmrung wach entgegenstarre, Ist diese da in süßem...","fid":"div__128"}]},{"docId":"D041283","docUri":"D041283.html","score":1,"contexts":[{"form":"Grauen","weight":"1","pos":51,"context":"...so ungütig. Es gibt Momente da mich ein <mark>Grauen<\/mark> fasst, wenn ich in diesen »Freundeskreis«...","fid":"p__25"}]}]}