{"stem":"hoher","instances":[{"docId":"T030023","docUri":"T030023.html","score":1,"contexts":[{"form":"hoher","weight":"1","pos":330,"context":"...entfernt. Herablassend, leutselig, immer wie ein <mark>hoher<\/mark> Herr, der einmal im schlichten Jägerrocke unter das...","fid":"p__13"}]},{"docId":"D041421","docUri":"D041421.html","score":1,"contexts":[{"form":"hoher","weight":"1","pos":216,"context":"...Causeur berühmt – was nicht? ein liebenswürdiger Mensch von <mark>hoher<\/mark> Anmut; der Wissenschaft, der Kunst und dem...","fid":"p__31"}]},{"docId":"D041468","docUri":"D041468.html","score":1,"contexts":[{"form":"hoher","weight":"1","pos":166,"context":"...der einem Torpedoboot glich, entgegenkam, um »auf <mark>hoher<\/mark> See« vom Schiff aus eine nach meinem Geschmack...","fid":"p__5"}]},{"docId":"L041648","docUri":"L041648.html","score":1,"contexts":[{"form":"hoher","weight":"1","pos":42,"context":"...erschwert durch die Tatsachen dass V. s Bruder in <mark>hoher<\/mark> montenegrinischer Staatsstellung ist, er selbst ein Gedicht verfasst und...","fid":"p__37"}]},{"docId":"D041598","docUri":"D041598.html","score":1,"contexts":[{"form":"hoher","weight":"1","pos":29,"context":"...um jeden Preis, dabei Angst zurückzubleiben, unverkennbar <mark>hoher<\/mark> Ernst (gerade dann fängt das Publicum zu lachen an);...","fid":"p__36"}]},{"docId":"D041481","docUri":"D041481.html","score":1,"contexts":[{"form":"Hoher","weight":"1","pos":89,"context":"Gräfin Thun <mark>Hoher<\/mark> Markt Palais Sina ","fid":"p__31"}]}]}