{"stem":"konferenz","instances":[{"docId":"L041593","docUri":"L041593.html","score":1,"contexts":[{"form":"Konferenz","weight":"1","pos":131,"context":"...der Empfänger dieser milden Spende voll Stolz in der <mark>Konferenz<\/mark> gezeigt hat. In diesem Anzuge wird er Sie festlich...","fid":"p__8"}]},{"docId":"L041546","docUri":"L041546.html","score":1,"contexts":[{"form":"Konferenz","weight":"1","pos":60,"context":"...und ich habe morgen vormittag auf der Bühne eine <mark>Konferenz<\/mark> mit Frank und Leffler, wo gewisse Sachen gleich...","fid":"p__34"}]}]}