{"stem":"kräftig","instances":[{"docId":"T030004","docUri":"T030004.html","score":1,"contexts":[{"form":"kräftig","weight":"1","pos":2119,"context":"» Sie war <mark>kräftig<\/mark> abgefaßt, unsere Hoffnungen, Wünsche und Weltverbesserungen keineswegs...","fid":"p__81"}]},{"docId":"L041670","docUri":"L041670.html","score":1,"contexts":[{"form":"kräftig","weight":"1","pos":192,"context":"...vollkommen entsprechende Bohème-Atmosphäre,– Schülein, der <mark>kräftig<\/mark> an der Börse spielt, und die beneideten outsider...","fid":"p__12"}]},{"docId":"T030040","docUri":"T030040.html","score":1,"contexts":[{"form":"kräftig","weight":"1","pos":89,"context":"...der bisher in der Sonne gesessen, groß und <mark>kräftig<\/mark> mit durchaus unregelmäßigem Gang, von Antlitz finster und...","fid":"p__20"}]}]}