{"stem":"nhil","instances":[{"docId":"T030085","docUri":"T030085.html","score":4,"contexts":[{"form":"Nhil","weight":"1","pos":11,"context":"Ich schätze Herrn Robert <mark>Nhil<\/mark>. Er spielt verständig, thut mit Eifer seine...","fid":"p__2"},{"form":"Nhil","weight":"1","pos":57,"context":"...Theater zeigen!« Aber er berief sich auf Herrn <mark>Nhil<\/mark>. Herr Nhil hatte gesagt: »Wenn sich die Wien...","fid":"p__13"},{"form":"Nhil","weight":"1","pos":59,"context":"...Aber er berief sich auf Herrn Nhil. Herr <mark>Nhil<\/mark> hatte gesagt: »Wenn sich die Wienerinnen das gefallen...","fid":"p__13"},{"form":"Nhil","weight":"1","pos":155,"context":"Herr <mark>Nhil<\/mark>, Herr Müller und Frau Schwerdtner sind nur ein...","fid":"p__15"}]},{"docId":"D041137","docUri":"D041137.html","score":1,"contexts":[{"form":"Nhil","weight":"1","pos":50,"context":"...zu sein als du. Warum bist du nicht auf <mark>Nhil<\/mark> oder Beer-Hofmann eifersüchtig?– Ich möchte dich...","fid":"p__14"}]},{"docId":"D041097","docUri":"D041097.html","score":1,"contexts":[{"form":"Nhil","weight":"1","pos":18,"context":"..., Willy, Olga Dv., Theodor Pollak, <mark>Nhil<\/mark>, Bahr; später Kraus; Schik.– Ich...","fid":"p__18"}]},{"docId":"D041100","docUri":"D041100.html","score":1,"contexts":[{"form":"Nhil","weight":"1","pos":7,"context":" 1\/4 War Mittag bei Dilly.– <mark>Nhil<\/mark>, Theo, Willy.–","fid":"p__6"}]},{"docId":"L041595","docUri":"L041595.html","score":1,"contexts":[{"form":"Nhil","weight":"1","pos":30,"context":"...Nerven können nicht strahlen. Du findest bei mir <mark>Nhil<\/mark> – und den kleinen Schnitzler – Wil ly  Bruder...","fid":"p__25"}]},{"docId":"T030010","docUri":"T030010.html","score":1,"contexts":[{"form":"Nhil","weight":"1","pos":1001,"context":"Herr  <mark>Nhil<\/mark>  schien heute ohne rechte Lust. Herr  Tewele ,...","fid":"p__41"}]}]}