{"stem":"orangen","instances":[{"docId":"T030081","docUri":"T030081.html","score":1,"contexts":[{"form":"Orangen","weight":"1","pos":541,"context":"...das andere Mal dabei. Burckhard begnügt sich meist mit <mark>Orangen<\/mark> und Artischoken.","fid":"p__29"}]},{"docId":"L041667","docUri":"L041667.html","score":1,"contexts":[{"form":"Orangen","weight":"1","pos":180,"context":"...ein entfliehen, ich war ein bischen unten, <mark>Orangen<\/mark> und Ansichtskarten kaufen, aber ich war so schwach...","fid":"p__6"}]}]}