{"stem":"polster","instances":[{"docId":"D041081","docUri":"D041081.html","score":1,"contexts":[{"form":"Polster","weight":"1","pos":22,"context":"...Ein Beleuchtungsobjekt von Trebitsch. Lampe von Liesl. <mark>Polster<\/mark> mit Photographie meiner Buchdeckel und meiner selbst von Benedicts...","fid":"p__7"}]},{"docId":"D041532","docUri":"D041532.html","score":1,"contexts":[{"form":"Polster","weight":"1","pos":11,"context":"...Blumen von Olga und Heini. Grüne Seidendecken, <mark>Polster<\/mark>, schöne Photographien von Heini (d’Ora).","fid":"p__6"}]}]}