{"stem":"quartett","instances":[{"docId":"D041296","docUri":"D041296.html","score":1,"contexts":[{"form":"Quartett","weight":"1","pos":15,"context":"Mittag mit Mama A moll <mark>Quartett<\/mark> Schubert.","fid":"p__8"}]},{"docId":"D041123","docUri":"D041123.html","score":1,"contexts":[{"form":"Quartett","weight":"1","pos":16,"context":"Beim böhm. <mark>Quartett<\/mark>.–","fid":"p__3"}]},{"docId":"D041540","docUri":"D041540.html","score":1,"contexts":[{"form":"Quartett","weight":"1","pos":19,"context":"Mit Heini Schumann <mark>Quartett<\/mark>.–","fid":"p__9"}]},{"docId":"D041501","docUri":"D041501.html","score":1,"contexts":[{"form":"Quartett","weight":"1","pos":11,"context":"Abd. mit O. <mark>Quartett<\/mark> Rosé – letztes Concert im Bösendorfersaal. Wir sprachen...","fid":"p__10"}]},{"docId":"D041265","docUri":"D041265.html","score":1,"contexts":[{"form":"Quartett","weight":"1","pos":25,"context":"...zu Tisch, nachher mit ihr 4h.  Borodin-<mark>Quartett<\/mark> .","fid":"p__5"}]},{"docId":"D041244","docUri":"D041244.html","score":1,"contexts":[{"form":"Quartett","weight":"1","pos":13,"context":"Mit Mama Nm. Op. 18 Nr. 5 <mark>Quartett<\/mark> Beethoven.–","fid":"p__6"}]},{"docId":"D041543","docUri":"D041543.html","score":1,"contexts":[{"form":"Quartett","weight":"1","pos":16,"context":"Mit Heini Mozart <mark>Quartett<\/mark>.– ","fid":"p__6"}]}]}