{"stem":"rumänen","instances":[{"docId":"T030026","docUri":"T030026.html","score":1,"contexts":[{"form":"Rumänen","weight":"1","pos":304,"context":"...Tschechen , die Ruthenen, die Kroaten, die <mark>Rumänen<\/mark>, die Slovenen und die Italiener und so weiter...","fid":"p__21"}]},{"docId":"T030039","docUri":"T030039.html","score":1,"contexts":[{"form":"Rumänen","weight":"1","pos":128,"context":"...Hier sind alle Slaven (die Polen abgerechnet), die <mark>Rumänen<\/mark>, die Italiener unterdrückt. Sie haben die Rechte...","fid":"p__26"}]}]}