{"stem":"rätselhaft","instances":[{"docId":"L041562","docUri":"L041562.html","score":1,"contexts":[{"form":"rätselhafte","weight":"1","pos":161,"context":"...« zusammenfassen könnte? Wobei mir der brave, aber <mark>rätselhafte<\/mark> Hugo von Hofmannsthal einfällt, der schon lange hier...","fid":"p__46"}]},{"docId":"T030004","docUri":"T030004.html","score":1,"contexts":[{"form":"rätselhaft","weight":"1","pos":1078,"context":"...die Zeit von dreißig bis vierzig, Mannesjahre voll <mark>rätselhaft<\/mark>-geheimer Formung des eigenen Ich bis zu dem...","fid":"p__36"}]},{"docId":"T030049","docUri":"T030049.html","score":1,"contexts":[{"form":"rätselhaft","weight":"1","pos":21,"context":"...so wenig hold, daß es mir heute ziemlich <mark>rätselhaft<\/mark> erscheint, wie es mir überhaupt gelang, in...","fid":"p__6"}]}]}