{"stem":"schönes","instances":[{"docId":"L041383","docUri":"L041383.html","score":2,"contexts":[{"form":"schönes","weight":"1","pos":88,"context":".... die Glyptothek, eine Sculpturensammlung angesehen und viel <mark>schönes<\/mark> gefunden, besonders antike Büsten. Abends um ½...","fid":"p__14"},{"form":"schönes","weight":"1","pos":249,"context":"...bei Regen hier angekommen. – Im Continental ein <mark>schönes<\/mark>, aber theures Zimmer. – In ein Wiener...","fid":"p__12"}]},{"docId":"L041560","docUri":"L041560.html","score":1,"contexts":[{"form":"Schönes","weight":"1","pos":107,"context":"...Sie arbeiten, Sie müssen bis 1914 noch sehr <mark>Schönes<\/mark> schreiben; aber nachher auch, bitte!","fid":"p__8"}]},{"docId":"T030004","docUri":"T030004.html","score":1,"contexts":[{"form":"schönes","weight":"1","pos":1676,"context":"So leitet Bahr diese Kritiken ein, und ein <mark>schönes<\/mark> Wort des Paracelsus ist an ihre Spitze gesetzt:...","fid":"p__60"}]},{"docId":"L041526","docUri":"L041526.html","score":1,"contexts":[{"form":"schönes","weight":"1","pos":137,"context":"...dass Sie diese wählten, erscheint mir wie ein <mark>schönes<\/mark> dankbares Grüssen, hinüber zu jenen Gegenden, die...","fid":"p__19"}]},{"docId":"L041133","docUri":"L041133.html","score":1,"contexts":[{"form":"schönes","weight":"1","pos":15,"context":"dein <mark>schönes<\/mark> Burkhardbuch, von dem mir die meisten Kapitel schon...","fid":"p__14"}]},{"docId":"L041664","docUri":"L041664.html","score":1,"contexts":[{"form":"schönes","weight":"1","pos":27,"context":"...mit einer Schülerin,– übrigens ein blondes, blühend <mark>schönes<\/mark> Geschöpf, aber seelisch vollkommen ahnungslos in ihrer fabelhaften...","fid":"p__7"}]},{"docId":"L041477","docUri":"L041477.html","score":1,"contexts":[{"form":"Schönes","weight":"1","pos":6,"context":"Etwas so <mark>Schönes<\/mark>, wie die Gestalt des Franzl und seiner beiden...","fid":"p__8"}]},{"docId":"L041393","docUri":"L041393.html","score":1,"contexts":[{"form":"schönes","weight":"1","pos":136,"context":"...Juden mit großem Vergnügen gelesen haben. Es ist ein <mark>schönes<\/mark> Vorwort zu einem Buch das heute glaub ich keiner...","fid":"p__9"}]},{"docId":"L041625","docUri":"L041625.html","score":1,"contexts":[{"form":"Schönes","weight":"1","pos":108,"context":"...könnte noch viel mehr sein, so unendlich Viel und <mark>Schönes<\/mark>, – er soll halten was sein Bild früher...","fid":"p__7"}]},{"docId":"D041252","docUri":"D041252.html","score":1,"contexts":[{"form":"schönes","weight":"1","pos":12,"context":"...Zemlinsky bei uns. O. sang ihm vor. Er fand <mark>schönes<\/mark> Material; die Stimme aber noch ganz unausgebildet –...","fid":"p__5"}]},{"docId":"D041586","docUri":"D041586.html","score":1,"contexts":[{"form":"schönes","weight":"1","pos":40,"context":"Lese Oldenbergs Indische Literatur: <mark>schönes<\/mark> Buch. Las ein sehr kurzsichtiges Buch des Kommerzienrats...","fid":"p__9"}]},{"docId":"D041449","docUri":"D041449.html","score":1,"contexts":[{"form":"Schönes","weight":"1","pos":96,"context":"<mark>Schönes<\/mark> mit M. erlebt, mit der E. begonnen,...","fid":"p__13"}]},{"docId":"L041109","docUri":"L041109.html","score":1,"contexts":[{"form":"schönes","weight":"1","pos":20,"context":"...hat. Auch Burkhard hat mir in St Gilgen viel <mark>schönes<\/mark> darüber gesagt. Ja so spricht man übereinander und sieht...","fid":"p__16"}]},{"docId":"L041662","docUri":"L041662.html","score":1,"contexts":[{"form":"schönes","weight":"1","pos":285,"context":"...Harta zu Fuss nach Morzg, das ist ein <mark>schönes<\/mark> Restaurant vor Hellbrunn, herrlicher Weg, in der wunderbarsten...","fid":"p__67"}]},{"docId":"L041672","docUri":"L041672.html","score":1,"contexts":[{"form":"schönes","weight":"1","pos":58,"context":"...gewaschen, sorgfältig Toilette gemacht, mein altes immer noch <mark>schönes<\/mark> graues Flöge-Kostüm, neuer grauer Hut,...","fid":"p__16"}]},{"docId":"D041076","docUri":"D041076.html","score":1,"contexts":[{"form":"schönes","weight":"1","pos":9,"context":"...O. spazieren. Sonnenwintertag. Skiläufer, Rodelleute, <mark>schönes<\/mark> Bild beim »Johann«.","fid":"p__4"}]},{"docId":"L041661","docUri":"L041661.html","score":1,"contexts":[{"form":"schönes","weight":"1","pos":13,"context":"...: also erst mit Zweig hinauf in sein wirklich <mark>schönes<\/mark>, hauptsächlich herrlich gelegenes altes Haus,– er hat...","fid":"p__14"}]},{"docId":"T030018","docUri":"T030018.html","score":1,"contexts":[{"form":"schönes","weight":"1","pos":724,"context":"...mich neu erschaffen? Verwandle mich, dir folg’ ich, <mark>schönes<\/mark> Bild!    Wie hättet Ihr, o Herr, und...","fid":"div__151"}]},{"docId":"L041547","docUri":"L041547.html","score":1,"contexts":[{"form":"schönes","weight":"1","pos":87,"context":"...der Conte Veith.) Wir haben hier endlich wieder <mark>schönes<\/mark> Wetter heut, und ich wünsche Ihnen ein gleiches...","fid":"p__25"}]},{"docId":"L041460","docUri":"L041460.html","score":1,"contexts":[{"form":"schönes","weight":"1","pos":161,"context":"...es eben auf die Hexameter ankommt. Sehr viel <mark>schönes<\/mark> in dem Epos, auch von dem überraschend gelungnen...","fid":"p__11"}]},{"docId":"L041055","docUri":"L041055.html","score":1,"contexts":[{"form":"schönes","weight":"1","pos":77,"context":"...: sage mir nichts »freundliches« oder »<mark>schönes<\/mark>« in deinem Widmungswort. Die Thatsache der Zu...","fid":"p__21"}]},{"docId":"L041667","docUri":"L041667.html","score":1,"contexts":[{"form":"schönes","weight":"1","pos":165,"context":"...humorvoll von ihrer ersten Communion, die sie als <mark>schönes<\/mark> Theater empfunden habe. ","fid":"p__8"}]}]}