{"stem":"titel","instances":[{"docId":"T030030","docUri":"T030030.html","score":2,"contexts":[{"form":"Titel","weight":"1","pos":57,"context":"..., denn schon das verpönte »Modern« im <mark>Titel<\/mark> kündigte den Bruch mit dem geheiligten Brauch an, auch...","fid":"p__87"},{"form":"Titel","weight":"1","pos":180,"context":"...Ausruf: » Das Schauspiel ist, wie auf dem <mark>Titel<\/mark> bemerkt steht, den Bühnen gegenüber Manuskript. Die Bühnen...","fid":"p__87"}]},{"docId":"L041540","docUri":"L041540.html","score":2,"contexts":[{"form":"Titel","weight":"1","pos":79,"context":"...Stücke und noch besser für meine Stimmung. Der <mark>Titel<\/mark> steht noch nicht fest. »Das Kind« ist...","fid":"p__12"},{"form":"Titel","weight":"1","pos":86,"context":"...« zu banal, jetzt halt ich bei dem <mark>Titel<\/mark> »In der Familie«.","fid":"p__12"}]},{"docId":"L041263","docUri":"L041263.html","score":2,"contexts":[{"form":"Titel","weight":"1","pos":10,"context":"...auf einer Correspondenzkarte, Auskunft geben, ob der <mark>Titel<\/mark> »Primarius« in Süddeutschland üblich ist und wie...","fid":"p__9"},{"form":"Titel","weight":"1","pos":20,"context":"...weiß es nicht und gibt vor an , den <mark>Titel<\/mark> überhaupt nie gehört zu haben.","fid":"p__9"}]},{"docId":"L041143","docUri":"L041143.html","score":2,"contexts":[{"form":"Titel","weight":"1","pos":23,"context":"...ich folgenderma ßen beantworten zu können glaube. Der <mark>Titel<\/mark> Primararzt ist fast nur in Oesterreich üblich. In...","fid":"p__11"},{"form":"Titel","weight":"1","pos":38,"context":"...Dr« oder mit dem fast jedem von ihnen verliehenen <mark>Titel<\/mark> »Medizinalrath« »Geh. M. R.« ev....","fid":"p__11"}]},{"docId":"L041208","docUri":"L041208.html","score":2,"contexts":[{"form":"Titel","weight":"1","pos":17,"context":"...Dir. Ich muß aber bis morgen Dienstag Abend die <mark>Titel<\/mark> haben, damit Donnerstag (Feiertag) die Ankündigung in...","fid":"p__16"},{"form":"Titel","weight":"1","pos":23,"context":"...in den Blättern sein kann. Schreibe mir also den <mark>Titel<\/mark> von Hirschfelds Geschichte sowie von Deine r , von...","fid":"p__16"}]},{"docId":"L041012","docUri":"L041012.html","score":1,"contexts":[{"form":"Titel","weight":"1","pos":7,"context":" Lieber Hermann, wie kann ich dir den <mark>Titel<\/mark> sagen, wenn ich noch nicht weiss was ich...","fid":"p__18"}]},{"docId":"L041377","docUri":"L041377.html","score":1,"contexts":[{"form":"Titel","weight":"1","pos":69,"context":"...die Dinge leichter vollbringen. Daß Blumenthal auch den <mark>Titel<\/mark> des Stücks geändert haben möchte, ist Caesarenwahnsinn. Es...","fid":"p__7"}]},{"docId":"L041480","docUri":"L041480.html","score":1,"contexts":[{"form":"Titel","weight":"1","pos":148,"context":"...Stücke. In allen dreien könnten vor allem die <mark>Titel<\/mark> gewechselt werden, ohne daß es ein Mensch merkt;...","fid":"p__6"}]},{"docId":"L041569","docUri":"L041569.html","score":1,"contexts":[{"form":"Titel","weight":"1","pos":20,"context":"...herzlich freue. Da möchte ich gerne den bisherigen <mark>Titel<\/mark>, der nicht von mir und gar zu journalistisch...","fid":"p__7"}]},{"docId":"T030041","docUri":"T030041.html","score":1,"contexts":[{"form":"Titel","weight":"1","pos":1789,"context":"...Präs. : Die Berliner können schon den <mark>Titel<\/mark> nicht aussprechen. (Heiterkeit.) ","fid":"p__104"}]},{"docId":"T030076","docUri":"T030076.html","score":1,"contexts":[{"form":"Titel","weight":"1","pos":61,"context":"...und Cynisches seltsam vermischenden Scene, die, unter dem <mark>Titel<\/mark> Anatol gesammelt, (1893) zuerst dem jungen...","fid":"p__17"}]},{"docId":"L041645","docUri":"L041645.html","score":1,"contexts":[{"form":"Titel","weight":"1","pos":212,"context":"...blinde Passagier«, letzterer unter dem he rr lichen <mark>Titel<\/mark>: »Le passager aveugle«.","fid":"p__35"}]},{"docId":"D041049","docUri":"D041049.html","score":1,"contexts":[{"form":"Titels","weight":"1","pos":38,"context":"...Cadol, das ich mir 97 in Paris des <mark>Titels<\/mark> halber (»Liebelei«) gekauft.","fid":"p__9"}]},{"docId":"L041204","docUri":"L041204.html","score":1,"contexts":[{"form":"Titel","weight":"1","pos":7,"context":"Kannst Du mir den <mark>Titel<\/mark> Deiner Novelle sofort mittheilen? Sie soll nemlich annonciert...","fid":"p__4"}]},{"docId":"L041387","docUri":"L041387.html","score":1,"contexts":[{"form":"Titel","weight":"1","pos":26,"context":"...in Wien eingefallen) u das vorläufig unter dem <mark>Titel<\/mark> »Das Kind« gehen soll. Abds im Wald...","fid":"p__11"}]},{"docId":"D041240","docUri":"D041240.html","score":1,"contexts":[{"form":"Titel","weight":"1","pos":33,"context":"...gelesen – N. E. (Neue Ehe, vorläufiger <mark>Titel<\/mark> für die 3aktige Komoedie) neu begonnen.–...","fid":"p__6"}]},{"docId":"T030033","docUri":"T030033.html","score":1,"contexts":[{"form":"Titel","weight":"1","pos":57,"context":"...Ewigkeit «, so sollte man meinen, daß allein dieser <mark>Titel<\/mark> schon meinen unerschütterlichen Glauben an Oesterreich offenbart, vielleicht...","fid":"p__37"}]},{"docId":"L041004","docUri":"L041004.html","score":1,"contexts":[{"form":"Titel","weight":"1","pos":24,"context":"...streiche aber keinesfalls selbst. Auch wenn dir ein wirksamerer <mark>Titel<\/mark> einfiele, so wäre mir das sehr willkommen....","fid":"p__7"}]}]}