{"stem":"türkenschanzpark","instances":[{"docId":"D041332","docUri":"D041332.html","score":1,"contexts":[{"form":"Türkenschanzpark","weight":"1","pos":56,"context":"Im <mark>Türkenschanzpark<\/mark> gen. mit Salten und Sohn; Dr. Menczel...","fid":"p__22"}]},{"docId":"D041557","docUri":"D041557.html","score":1,"contexts":[{"form":"Türkenschanzpark","weight":"1","pos":46,"context":"Kinder, mit Ruthen, am <mark>Türkenschanzpark<\/mark>, im Takt schlagend: »Noch ein Jud –...","fid":"p__7"}]},{"docId":"D041536","docUri":"D041536.html","score":1,"contexts":[{"form":"Türkenschanzpark","weight":"1","pos":58,"context":"...P. Kino – die kleine Sklavin; dann im <mark>Türkenschanzpark<\/mark> (innen;– Regen) soup.","fid":"p__7"}]},{"docId":"D041233","docUri":"D041233.html","score":1,"contexts":[{"form":"Türkenschanzpark","weight":"1","pos":38,"context":"...mit ihm und O. auf dem Balkon, dann <mark>Türkenschanzpark<\/mark> – Über den Marsyas; Literaten, Künstler;...","fid":"p__15"}]},{"docId":"D041232","docUri":"D041232.html","score":1,"contexts":[{"form":"Türkenschanzpark","weight":"1","pos":62,"context":"...»Hat den Bluthund endlich sein Schicksal ereilt –« Im <mark>Türkenschanzpark<\/mark> soupirt –","fid":"p__17"}]},{"docId":"T030081","docUri":"T030081.html","score":1,"contexts":[{"form":"Türkenschanzpark","weight":"1","pos":642,"context":"...mich zuweilen, meist von seinem gewohnten Spaziergang im <mark>Türkenschanzpark<\/mark> an unserm Haus vorüberkommend. Anfangs war er immer...","fid":"p__29"}]},{"docId":"L041393","docUri":"L041393.html","score":1,"contexts":[{"form":"Türkenschanzpark","weight":"1","pos":13,"context":"...war Sonntag bei uns, dann haben wir zusammen im <mark>Türkenschanzpark<\/mark> genachtmahlt und er war in der besten Stimmung....","fid":"p__12"}]},{"docId":"D041148","docUri":"D041148.html","score":1,"contexts":[{"form":"Türkenschanzpark","weight":"1","pos":18,"context":"...lieber.– Neulich war er mit Bahr und dessen Frau <mark>Türkenschanzpark<\/mark>. B. erwähnte, dass ich ihm hier den...","fid":"p__24"}]},{"docId":"D041252","docUri":"D041252.html","score":1,"contexts":[{"form":"Türkenschanzpark","weight":"1","pos":5,"context":" 17\/6 Vm. im <mark>Türkenschanzpark<\/mark>, las Schreyvogels Tagebuch.","fid":"p__6"}]},{"docId":"D041065","docUri":"D041065.html","score":1,"contexts":[{"form":"Türkenschanzpark","weight":"1","pos":38,"context":"– Mit O. spazieren <mark>Türkenschanzpark<\/mark>. Treffen Salten mit Otti und Töchterl. Er...","fid":"p__24"}]}]}