{"stem":"unannehmlichkeit","instances":[{"docId":"D041077","docUri":"D041077.html","score":1,"contexts":[{"form":"Unannehmlichkeit","weight":"1","pos":25,"context":"..., empfindet sein »Gebrechen« nur als gelegentliche <mark>Unannehmlichkeit<\/mark> – die »sentimentale Auffassung« seines Leidens soll...","fid":"p__4"}]},{"docId":"D041084","docUri":"D041084.html","score":1,"contexts":[{"form":"Unannehmlichkeit","weight":"1","pos":11,"context":"...Ich liebe sie doch viel zu wenig, um die <mark>Unannehmlichkeit<\/mark>, in der Nacht in der größten Kälte von...","fid":"p__4"}]}]}