{"stem":"ungemüthlich","instances":[{"docId":"T030011","docUri":"T030011.html","score":1,"contexts":[{"form":"ungemüthliche","weight":"1","pos":482,"context":"...Laune des ersten Actes wurde durch eine forcierte und <mark>ungemüthliche<\/mark> Lustigkeit mit Gepolter und Tapage gestört. Dem lieben...","fid":"p__19"}]},{"docId":"L041535","docUri":"L041535.html","score":1,"contexts":[{"form":"ungemüthlich","weight":"1","pos":150,"context":"...unerträglich – kaltes abscheuliches Wetter – Willy ist sehr <mark>ungemüthlich<\/mark> – sie war unlängst in Wien, wo ihr...","fid":"p__23"}]}]}