{"stem":"wasser","instances":[{"docId":"T030014","docUri":"T030014.html","score":2,"contexts":[{"form":"Wasser","weight":"1","pos":223,"context":"...eifersüchtigen Mann, eine Villa, leuchtend und weiß am <mark>Wasser<\/mark>, mit einer berühmten Platane im Park, unter...","fid":"p__8"},{"form":"Wasser","weight":"1","pos":387,"context":"...Amadeus zu seiner kleinen Gräfin in die weiß am <mark>Wasser<\/mark> leuchtende Villa unter die berühmte Platane. Das hält...","fid":"p__17"}]},{"docId":"L041572","docUri":"L041572.html","score":1,"contexts":[{"form":"Wasser","weight":"1","pos":20,"context":"...Bodensee? An und für sich macht so ein <mark>Wasser<\/mark> nervöse Leute noch trauriger und alle Abende werden trüber...","fid":"p__19"}]},{"docId":"L041657","docUri":"L041657.html","score":1,"contexts":[{"form":"Wasser","weight":"1","pos":157,"context":"...wie alles, worin von einem der Wein trinkt, <mark>Wasser<\/mark> gepredigt wird (was hier fast wörtlich zu nehmen ist))...","fid":"p__13"}]},{"docId":"L041373","docUri":"L041373.html","score":1,"contexts":[{"form":"Wasser","weight":"1","pos":80,"context":"...ich für den Sommer vorhabe (Holland, zu <mark>Wasser<\/mark> nach Kiel) Die Radtour könnte auch durch einige...","fid":"p__32"}]},{"docId":"L041585","docUri":"L041585.html","score":1,"contexts":[{"form":"Wasser","weight":"1","pos":47,"context":"...heftig und störend. Nerven wieder schlechter trotz kaltem <mark>Wasser<\/mark> etc.– Erheiterung brachte ein » Novellenband « vom...","fid":"p__19"}]},{"docId":"L041391","docUri":"L041391.html","score":1,"contexts":[{"form":"Wasser","weight":"1","pos":51,"context":"...gleich zurückfuhren. Die andern Seen fielen sozusagen ins <mark>Wasser<\/mark>, was sie doch gar nicht mehr notwendig haben....","fid":"p__35"}]},{"docId":"L041660","docUri":"L041660.html","score":1,"contexts":[{"form":"Wasser","weight":"1","pos":312,"context":"...das ihre mit Bad, allerdings läuft kein warmes <mark>Wasser<\/mark>, – 18 Kronen, – per Mahlzeit 12...","fid":"p__15"}]},{"docId":"D041428","docUri":"D041428.html","score":1,"contexts":[{"form":"Wasser","weight":"1","pos":203,"context":"...das Schiff ab, die andere stürzt, fallen ins <mark>Wasser<\/mark>. Ich lag Stunden lang, heftig erbrechend. In...","fid":"p__15"}]},{"docId":"L041427","docUri":"L041427.html","score":1,"contexts":[{"form":"Wasser","weight":"1","pos":59,"context":"...hoffe ich manches Schöne: Sonne und Mond am <mark>Wasser<\/mark>, Segeln, kindlich-lärmende Vergnügungen, Richard...","fid":"p__7"}]},{"docId":"L041641","docUri":"L041641.html","score":1,"contexts":[{"form":"Wasser","weight":"1","pos":49,"context":"...sie charmant. Aber ich will keinen Schlag in’s <mark>Wasser<\/mark> thun, weshalb ich noch nicht über den Star...","fid":"p__42"}]},{"docId":"T030020","docUri":"T030020.html","score":1,"contexts":[{"form":"Wasser","weight":"1","pos":799,"context":"...rasch. Das verlockend wirre Spiel, wie dunkles <mark>Wasser<\/mark> tief, ist aus.","fid":"p__14"}]}]}