{"stem":"winter","instances":[{"docId":"L041356","docUri":"L041356.html","score":2,"contexts":[{"form":"Winter","weight":"1","pos":9,"context":"Nun ist der <mark>Winter<\/mark> mit Macht eingebrochen und es scheint, daß wir...","fid":"p__6"},{"form":"Winter","weight":"1","pos":28,"context":"...Jugenderinnerungen an Salzburg hegend, wo man ja im <mark>Winter<\/mark>, wies schneit, wenn man auf der Brücke...","fid":"p__6"}]},{"docId":"T030081","docUri":"T030081.html","score":2,"contexts":[{"form":"Winter","weight":"1","pos":549,"context":"...Herbst 1905 (?) besuchen wir ihn dort. Ebenso im <mark>Winter<\/mark> desselben Jahres. Rodeln hinter seinem Haus. Seine...","fid":"p__46"},{"form":"Winter","weight":"1","pos":655,"context":"...verloren sie sich beinahe regelmässig und noch im vergangenen <mark>Winter<\/mark> wurde man manchmal an seine besten Tage erinnert....","fid":"p__29"}]},{"docId":"L041393","docUri":"L041393.html","score":2,"contexts":[{"form":"Winters","weight":"1","pos":48,"context":"...bringen, dass er heuer die verschiedenen Erregungen des <mark>Winters<\/mark> u den Winter selbst nicht zu Hause abwartet und...","fid":"p__12"},{"form":"Winter","weight":"1","pos":49,"context":"...er heuer die verschiedenen Erregungen des Winters u den <mark>Winter<\/mark> selbst nicht zu Hause abwartet und zu guter Zeit...","fid":"p__12"}]},{"docId":"L041674","docUri":"L041674.html","score":2,"contexts":[{"form":"Winter","weight":"1","pos":47,"context":"Der <mark>Winter<\/mark> ist wie im Flug vergangen, und ausser ein...","fid":"p__3"},{"form":"Winter","weight":"1","pos":353,"context":"...rächt sich. Die Pension Jaeger, die über den <mark>Winter<\/mark> nicht in Function war, eröffnet jetzt am 1. März...","fid":"p__20"}]},{"docId":"T030030","docUri":"T030030.html","score":1,"contexts":[{"form":"Winter","weight":"1","pos":17,"context":"...1889 in Paris, als ich eben über den <mark>Winter<\/mark> nach Spanien und Marokko ging, erhielt ich einen Brief...","fid":"p__87"}]},{"docId":"D041291","docUri":"D041291.html","score":1,"contexts":[{"form":"Winter","weight":"1","pos":33,"context":"Traf Dr. J. <mark>Winter<\/mark>; der mir nächstens die zur Herausgabe bestimmte Gedichtsammlung...","fid":"p__5"}]},{"docId":"T030028","docUri":"T030028.html","score":1,"contexts":[{"form":"Winter","weight":"1","pos":76,"context":"...blättern: man saß, während sich draußen der <mark>Winter<\/mark> um die Scheiben immer weißer stöbernd zusammenzog, behaglich...","fid":"p__10"}]},{"docId":"L041666","docUri":"L041666.html","score":1,"contexts":[{"form":"Winter","weight":"1","pos":255,"context":"...mir von den Heizcalamitäten erzälte, er wird im <mark>Winter<\/mark> vielleicht die Küche sperren müssen,– selbst wenn ich ein...","fid":"p__11"}]},{"docId":"D041555","docUri":"D041555.html","score":1,"contexts":[{"form":"Winter","weight":"1","pos":6,"context":" 26\/9 Vm. Intendanz bei Dr. <mark>Winter<\/mark>, auf seine Bitte. Er wollte meine Fürsprache...","fid":"p__10"}]},{"docId":"T030004","docUri":"T030004.html","score":1,"contexts":[{"form":"Winter","weight":"1","pos":3295,"context":"Im <mark>Winter<\/mark> 1921: Salzburg im Schnee. So stumm und...","fid":"p__114"}]},{"docId":"D041348","docUri":"D041348.html","score":1,"contexts":[{"form":"Winter","weight":"1","pos":54,"context":"...Leben hier oben – insbesondre von der Einsamkeit im <mark>Winter<\/mark>, der fast unerträglichen Concentration, den Depressionen.–...","fid":"p__18"}]},{"docId":"D041296","docUri":"D041296.html","score":1,"contexts":[{"form":"Winter","weight":"1","pos":28,"context":"...Wien gesprochen. Jetzt ist er seit 10 J. <mark>Winter<\/mark> in Assuan, erzählte uns dann rührend-sächselnd...","fid":"p__13"}]},{"docId":"D041042","docUri":"D041042.html","score":1,"contexts":[{"form":"Winter","weight":"1","pos":67,"context":"Der <mark>Winter<\/mark> mit seiner Kälte scheint mir endlos. Ich schlafe...","fid":"p__6"}]},{"docId":"L041384","docUri":"L041384.html","score":1,"contexts":[{"form":"Winter","weight":"1","pos":40,"context":"...erst im Frühjahr in Erfüllung gehen, denn unser grauer <mark>Winter<\/mark> lastet diesmal auffallend schwer auf meiner Stimmung und meinem...","fid":"p__18"}]},{"docId":"D041429","docUri":"D041429.html","score":1,"contexts":[{"form":"Winter","weight":"1","pos":21,"context":"...die Mutter sagt: denk nur, was wir für einen <mark>Winter<\/mark> verbracht hätten, wenn uns nicht Aphrodite diesen geschickt hätte....","fid":"p__6"}]},{"docId":"L041373","docUri":"L041373.html","score":1,"contexts":[{"form":"Winter","weight":"1","pos":38,"context":"...aber auch a tempo: es ist   seit langem <mark>Winter<\/mark> wieder die erste Frühlingswärme, die erste Sonne wieder...","fid":"p__32"}]},{"docId":"L041618","docUri":"L041618.html","score":1,"contexts":[{"form":"Winter","weight":"1","pos":122,"context":"...Marie; und ich glaube, sie wird im <mark>Winter<\/mark> wieder bei uns spielen (Dies aber völlig unter uns,...","fid":"p__31"}]},{"docId":"T030027","docUri":"T030027.html","score":1,"contexts":[{"form":"Winter","weight":"1","pos":48,"context":"...Art können Sie nirgends was Besseres sehen!« Im <mark>Winter<\/mark>, wenn die Fremden wieder fort und wir wieder...","fid":"p__12"}]},{"docId":"L041188","docUri":"L041188.html","score":1,"contexts":[{"form":"Winter","weight":"1","pos":21,"context":"...als aus einem Buche stammend, das den nächsten <mark>Winter<\/mark> erst deutsch erscheinen soll, von ihm autorisiert, ja...","fid":"p__8"}]},{"docId":"D041058","docUri":"D041058.html","score":1,"contexts":[{"form":"Winter","weight":"1","pos":42,"context":".... Das Publikum. Sprach Dr. Feuchtwang und Josef <mark>Winter<\/mark>. Warteten den Trauerzug ab, gingen dann. Welche Sinnlosigkeit...","fid":"p__7"}]},{"docId":"L041664","docUri":"L041664.html","score":1,"contexts":[{"form":"Winter","weight":"1","pos":147,"context":"...der Halle, – Frau H. die den ganzen <mark>Winter<\/mark> hier bleibt und ihr Hietzinger Haus vermietet,–...","fid":"p__17"}]},{"docId":"L041645","docUri":"L041645.html","score":1,"contexts":[{"form":"Winter","weight":"1","pos":175,"context":"...brachte ich es wenigstens so weit, daß Antoine diesen <mark>Winter<\/mark> Lear in einer Bearbeitung Pierre Lotis spielen wird,...","fid":"p__35"}]},{"docId":"D041431","docUri":"D041431.html","score":1,"contexts":[{"form":"Winter","weight":"1","pos":108,"context":"...ein bischen Motion zu machen. Dies will ich diesen <mark>Winter<\/mark> tun.","fid":"p__13"}]},{"docId":"L041684","docUri":"L041684.html","score":1,"contexts":[{"form":"Winter","weight":"1","pos":128,"context":"Hoffentlich sieht man Sie, noch ehe der <mark>Winter<\/mark> zu Ende geht, noch einmal in Berlin, und...","fid":"p__9"}]},{"docId":"D041326","docUri":"D041326.html","score":1,"contexts":[{"form":"Winter","weight":"1","pos":28,"context":"...in Berlin, Barnowskys Unverläßlichkeiten).– Intendanz bei Dr. <mark>Winter<\/mark>; er ist noch immer unsicher über seine Zukunft...","fid":"p__23"}]},{"docId":"L041660","docUri":"L041660.html","score":1,"contexts":[{"form":"Winter","weight":"1","pos":280,"context":"...hat sich dort zuständig erklären lassen und verbringen den <mark>Winter<\/mark> dort.","fid":"p__13"}]},{"docId":"L041463","docUri":"L041463.html","score":1,"contexts":[{"form":"Winter","weight":"1","pos":39,"context":"...als zu einem Buche gehörend, das im kommenden <mark>Winter<\/mark> zum ersten Mal in deutscher Sprache publiciert werden...","fid":"p__23"}]},{"docId":"L041458","docUri":"L041458.html","score":1,"contexts":[{"form":"Winter","weight":"1","pos":116,"context":"...Factur, besonders klug u sympathisch (sind für den <mark>Winter<\/mark> in Wien). Von Pierre Loving hab ich dir...","fid":"p__17"}]},{"docId":"L041662","docUri":"L041662.html","score":1,"contexts":[{"form":"Winter","weight":"1","pos":146,"context":"...sehr reiche Frau (Möbelhändler Hermann) bleibt diesen <mark>Winter<\/mark> hier etc.) sassen die 3 Herren nebenan in...","fid":"p__67"}]},{"docId":"D041178","docUri":"D041178.html","score":1,"contexts":[{"form":"Winter","weight":"1","pos":9,"context":"...Abd. »Josefine« von Bahr : mit <mark>Winter<\/mark>, später Kapper’s und Schik (wir reichten uns nach...","fid":"p__10"}]},{"docId":"D041083","docUri":"D041083.html","score":1,"contexts":[{"form":"Winter","weight":"1","pos":6,"context":" 30\/10 Interpellation <mark>Winter<\/mark>, Hanusch Genossen (mir alle unbekannt), wegen Bernhardi...","fid":"p__6"}]},{"docId":"L041312","docUri":"L041312.html","score":1,"contexts":[{"form":"Winter","weight":"1","pos":18,"context":"...die herzlichsten Grüsse und alle guten Wünsche für den <mark>Winter<\/mark> schicken. Ich möchte Dir noch sagen, dass...","fid":"p__13"}]},{"docId":"D041154","docUri":"D041154.html","score":1,"contexts":[{"form":"Winter","weight":"1","pos":22,"context":"...sehr gut. Vis à vis vom Burgth.– <mark>Winter<\/mark>, Arth. Klein, Frau Mautner kam von...","fid":"p__14"}]},{"docId":"D041142","docUri":"D041142.html","score":1,"contexts":[{"form":"Winter","weight":"1","pos":27,"context":"...sein; aber ich glaub es diesmal.– Nm. Josef <mark>Winter<\/mark> da, Bewunderung über »Sterben« ausdrücken.– Ein...","fid":"p__10"}]}]}